[{"domain": "globalnews.ca", "expiry": 1751712909, "httpOnly": false, "name": "_evidon_consent_cookie", "path": "/", "sameSite": "Lax", "secure": false, "value": "{\"consent_date\":\"2024-06-05T10:55:09.749Z\",\"gpc\":0,\"consent_type\":1}"}, {"domain": ".globalnews.ca", "httpOnly": false, "name": "s_sq", "path": "/", "sameSite": "Lax", "secure": false, "value": "corus-tv-globalnews%3D%2526c.%2526a.%2526activitymap.%2526page%253Dhttps%25253A%25252F%25252Fglobalnews.ca%25252F%2526link%253DACCEPT%2526region%253D_evidon_banner%2526.activitymap%2526.a%2526.c%2526pid%253Dhttps%25253A%25252F%25252Fglobalnews.ca%25252F%2526oid%253DfunctionN%252528Z%252529%25257Bif%252528I%252529%25257BclearTimeout%252528I%252529%25257DP%252528Z%252529%25253Bwindow.evidon.notice.dropPixel%252528e%252529%25253Bwindow.evidon.notice.postV%2526oidt%253D2%2526ot%253DSUBMIT"}, {"domain": ".globalnews.ca", "expiry": 1752144907, "httpOnly": false, "name": "sophiTagid.c459", "path": "/", "sameSite": "None", "secure": true, "value": "cfcbadb5-c1c1-4531-8c94-3a6cb0a6755a.1717584906.1.1717584907.1717584906.c398f249-cb38-4ac7-8907-9eb104ad2d00"}, {"domain": "globalnews.ca", "expiry": 1749120907, "httpOnly": false, "name": "__browsiUID", "path": "/", "sameSite": "Lax", "secure": false, "value": "75aeca7f-0478-40ba-8312-9e8882262b89"}, {"domain": ".globalnews.ca", "expiry": 1752144907, "httpOnly": false, "name": "AMCV_5F34123F5245B4A70A490D45%40AdobeOrg", "path": "/", "sameSite": "Lax", "secure": false, "value": "1585540135%7CMCMID%7C52402307479176422880881130883990426969%7CMCAAMLH-1718189707%7C6%7CMCAAMB-1718189707%7C6G1ynYcLPuiQxYZrsz_pkqfLG9yMXBpb2zX5dvJdYQJzPXImdj0y%7CMCOPTOUT-1717592107s%7CNONE%7CvVersion%7C4.4.0"}, {"domain": ".globalnews.ca", "httpOnly": false, "name": "AMCVS_5F34123F5245B4A70A490D45%40AdobeOrg", "path": "/", "sameSite": "Lax", "secure": false, "value": "1"}, {"domain": "globalnews.ca", "expiry": 1725360907, "httpOnly": false, "name": "_wpcom_geo", "path": "/", "sameSite": "Lax", "secure": false, "value": "gnca-national"}, {"domain": "globalnews.ca", "expiry": 1720176906, "httpOnly": false, "name": "vip-go-seg", "path": "/", "sameSite": "Lax", "secure": false, "value": "vc-v1__gnca-region_--_gnca-national"}, {"domain": ".globalnews.ca", "expiry": 1752144907, "httpOnly": false, "name": "_sp_duid", "path": "/", "sameSite": "None", "secure": true, "value": "cfcbadb5-c1c1-4531-8c94-3a6cb0a6755a"}, {"domain": ".globalnews.ca", "expiry": 1733399707, "httpOnly": false, "name": "permutive-id", "path": "/", "sameSite": "None", "secure": true, "value": "ee8b8c83-78a8-47bd-8052-81ac690b2211"}, {"domain": ".globalnews.ca", "expiry": 1717586707, "httpOnly": false, "name": "sophiTagses.c459", "path": "/", "sameSite": "None", "secure": true, "value": "*"}, {"domain": ".globalnews.ca", "expiry": 1751712907, "httpOnly": false, "name": "_chartbeat2", "path": "/", "sameSite": "Lax", "secure": true, "value": ".1717584906344.1717584907156.1.9WhHhdCWwyDNtSgSD5HnAdDNPCYi.2"}, {"domain": "globalnews.ca", "expiry": 1717586707, "httpOnly": false, "name": "__browsiSessionID", "path": "/", "sameSite": "Lax", "secure": false, "value": "530c9832-71da-477f-9fea-7e0d357f6e43&false&false&DEFAULT&gb&desktop-4.25.21&false"}, {"domain": ".globalnews.ca", "expiry": 1749207307, "httpOnly": false, "name": "_vwo_uuid_v2", "path": "/", "sameSite": "Lax", "secure": false, "value": "D648A8CF1CC56EE409C73D573DDC27E04|0ff7aacb37de9f0b5015c0282360b8a2"}, {"domain": ".globalnews.ca", "expiry": 1717586707, "httpOnly": false, "name": "_cb_svref", "path": "/", "sameSite": "Lax", "secure": true, "value": "external"}, {"domain": "globalnews.ca", "expiry": 1725360907, "httpOnly": false, "name": "gn-weatherRegion", "path": "/", "sameSite": "Lax", "secure": false, "value": "CAXX0504"}, {"domain": ".globalnews.ca", "expiry": 1733136907, "httpOnly": false, "name": "__eoi", "path": "/", "sameSite": "Lax", "secure": false, "value": "ID=d4cc44597a7a5921:T=1717584907:RT=1717584907:S=AA-AfjZWcRSCOjbuga-NTtpD6HWI"}, {"domain": "globalnews.ca", "expiry": 1722768907, "httpOnly": false, "name": "_wpcom_geo_exp", "path": "/", "sameSite": "Lax", "secure": false, "value": "gnca-national"}, {"domain": ".globalnews.ca", "httpOnly": false, "name": "s_cc", "path": "/", "sameSite": "Lax", "secure": false, "value": "true"}, {"domain": ".globalnews.ca", "expiry": 1751712907, "httpOnly": false, "name": "_cb", "path": "/", "sameSite": "Lax", "secure": true, "value": "DWcyO_ZeFhPCoLgJ6"}, {"domain": "globalnews.ca", "expiry": 1717671306, "httpOnly": false, "name": "gncaGeoDetected", "path": "/", "sameSite": "Lax", "secure": false, "value": "1"}]