[{"domain": ".wsj.com", "expiry": 1744295367, "httpOnly": false, "name": "consentDate", "path": "/", "sameSite": "None", "secure": true, "value": "2024-04-10T14:29:27.718Z"}, {"domain": ".wsj.com", "expiry": 1746887363, "httpOnly": false, "name": "_pctx", "path": "/", "sameSite": "Lax", "secure": true, "value": "%7Bu%7DN4IgrgzgpgThIC4B2YA2qA05owMoBcBDfSREQpAeyRCwgEt8oBJAEzIE4AmHgZgEYAHADZ%2BvQQFYuAFhEcADPJABfIA"}, {"domain": ".wsj.com", "expiry": 1744295367, "httpOnly": false, "name": "consentUUID", "path": "/", "sameSite": "None", "secure": true, "value": "beeb7b1e-923a-4d99-bd40-0c94b82d7d39_30"}, {"domain": "www.wsj.com", "expiry": 1712845763, "httpOnly": false, "name": "_lr_geo_location_state", "path": "/", "sameSite": "Lax", "secure": false, "value": "NH"}, {"domain": ".wsj.com", "httpOnly": false, "name": "AMCVS_CB68E4BA55144CAA0A4C98A5%40AdobeOrg", "path": "/", "sameSite": "Lax", "secure": false, "value": "1"}, {"domain": ".wsj.com", "expiry": 1747319363, "httpOnly": false, "name": "ab_uuid", "path": "/", "sameSite": "Lax", "secure": false, "value": "c0be4506-df5e-4bc1-8cd0-95c1d4c0b1ef"}, {"domain": ".wsj.com", "expiry": 1746887364, "httpOnly": false, "name": "cX_G", "path": "/", "sameSite": "Lax", "secure": true, "value": "cx%3A1tl0irdvhja552zeuvlmgsjxmz%3A1i20e3mydobe4"}, {"domain": ".wsj.com", "expiry": 1744295363, "httpOnly": false, "name": "_sp_su", "path": "/", "sameSite": "None", "secure": true, "value": "false"}, {"domain": ".wsj.com", "expiry": 1744295378, "httpOnly": false, "name": "datadome", "path": "/", "sameSite": "Lax", "secure": true, "value": "hYo2pxmFdBIhPos9edII00ARaEoqKha3gGj~Q93F993hpW1rVnsall6N7a6ElMbjO4zsqCFsQ082QkXKn6HXQZcAUMzNB672OXlEnH9O2Rp7bd9ht6Z82i_AgFBeIT9X"}, {"domain": ".wsj.com", "httpOnly": false, "name": "gdprApplies", "path": "/", "sameSite": "Lax", "secure": false, "value": "true"}, {"domain": ".wsj.com", "expiry": 1747319364, "httpOnly": false, "name": "AMCV_CB68E4BA55144CAA0A4C98A5%40AdobeOrg", "path": "/", "sameSite": "Lax", "secure": false, "value": "1585540135%7CMCIDTS%7C19824%7CMCMID%7C54058488430134099414515040933443377381%7CMCAID%7CNONE%7CMCOPTOUT-1712766564s%7CNONE%7CMCAAMLH-1713364164%7C6%7CMCAAMB-1713364164%7CRKhpRz8krg2tLO6pguXWp5olkAcUniQYPHaMWWgdJ3xzPWQmdj0y%7CMCSYNCSOP%7C411-19831%7CvVersion%7C4.4.0"}, {"domain": ".wsj.com", "expiry": 1712762963, "httpOnly": false, "name": "usr_prof_v2", "path": "/", "sameSite": "Lax", "secure": false, "value": "eyJpYyI6MX0%3D"}, {"domain": ".wsj.com", "expiry": 1744295363, "httpOnly": false, "name": "signedLspa", "path": "/", "sameSite": "None", "secure": true, "value": "undefined"}, {"domain": ".wsj.com", "httpOnly": false, "name": "vcdpaApplies", "path": "/", "sameSite": "Lax", "secure": false, "value": "false"}, {"domain": ".wsj.com", "expiry": 1744295363, "httpOnly": false, "name": "dnsDisplayed", "path": "/", "sameSite": "None", "secure": true, "value": "undefined"}, {"domain": "www.wsj.com", "expiry": 1712759668, "httpOnly": false, "name": "dicbo_id", "path": "/", "sameSite": "Lax", "secure": false, "value": "%7B%22dicbo_fetch%22%3A1712759368364%7D"}, {"domain": "www.wsj.com", "httpOnly": false, "name": "djvideovol", "path": "/", "sameSite": "Lax", "secure": false, "value": "1"}, {"domain": ".wsj.com", "expiry": 1746887363, "httpOnly": false, "name": "_pcid", "path": "/", "sameSite": "Lax", "secure": true, "value": "%7B%22browserId%22%3A%22lutwpb52hbqc59jb%22%7D"}, {"domain": ".wsj.com", "expiry": 1746887365, "httpOnly": false, "name": "cX_P", "path": "/", "sameSite": "Lax", "secure": true, "value": "lutwpb52hbqc59jb"}, {"domain": ".wsj.com", "expiry": 1744295363, "httpOnly": false, "name": "ccpaApplies", "path": "/", "sameSite": "None", "secure": true, "value": "false"}, {"domain": ".wsj.com", "expiry": 1715351362, "httpOnly": false, "name": "wsjregion", "path": "/", "sameSite": "Lax", "secure": false, "value": "na%2Cus"}, {"domain": ".wsj.com", "expiry": 1744295371, "httpOnly": false, "name": "utag_main", "path": "/", "sameSite": "Lax", "secure": false, "value": "v_id:018ec869e8b4001417f425d9fef105075001406d00bd0$_sn:1$_se:2$_ss:0$_st:1712761171970$ses_id:1712759367861%3Bexp-session$_pn:1%3Bexp-session$_prevpage:WSJ_Home_US%20Home%20Page%3Bexp-1712762971972$vapi_domain:wsj.com"}, {"domain": ".wsj.com", "httpOnly": false, "name": "regulationApplies", "path": "/", "sameSite": "Lax", "secure": false, "value": "gdpr%3Atrue%2Ccpra%3Afalse%2Cvcdpa%3Afalse"}, {"domain": "www.wsj.com", "expiry": 1712845763, "httpOnly": false, "name": "_lr_geo_location", "path": "/", "sameSite": "Lax", "secure": false, "value": "NL"}, {"domain": ".wsj.com", "expiry": 1712762965, "httpOnly": false, "name": "DJSESSION", "path": "/", "sameSite": "Lax", "secure": false, "value": "country%3Dnl%7C%7Ccontinent%3Deu%7C%7Cregion%3Dnh%7C%7Czip%3D1012"}]