[{"domain": ".aritzia.com", "expiry": 1755886880, "httpOnly": false, "name": "forterToken", "path": "/", "sameSite": "Lax", "secure": false, "value": "a4323540f7f1419ab63daca98542950e_1721326880130__UDF43_15ck_"}, {"domain": ".aritzia.com", "expiry": 1755886880, "httpOnly": false, "name": "OptanonConsent", "path": "/", "sameSite": "Lax", "secure": false, "value": "isGpcEnabled=0&datestamp=Thu+Jul+18+2024+20%3A21%3A20+GMT%2B0200+(Midden-Europese+zomertijd)&version=202401.1.0&browserGpcFlag=0&isIABGlobal=false&hosts=&consentId=a273f587-8808-4cf9-887a-b040e83d5019&interactionCount=1&landingPath=NotLandingPage&groups=C0001%3A1%2CC0003%3A1%2CC0002%3A1%2CC0004%3A1&geolocation=US%3B&AwaitingReconsent=false"}, {"domain": ".aritzia.com", "httpOnly": false, "name": "ADRUM", "path": "/", "sameSite": "Lax", "secure": true, "value": "s~1721326879282&r~aHR0cHMlM0ElMkYlMkZ3d3cuYXJpdHppYS5jb20lMkY="}, {"domain": ".aritzia.com", "expiry": 1723918880, "httpOnly": false, "name": "_dy_toffset", "path": "/", "sameSite": "Lax", "secure": false, "value": "0"}, {"domain": ".aritzia.com", "expiry": 1723918880, "httpOnly": false, "name": "_dy_df_geo", "path": "/", "sameSite": "Lax", "secure": false, "value": "United%20States.California.Los%20Angeles"}, {"domain": ".aritzia.com", "expiry": 1723918880, "httpOnly": false, "name": "_dycst", "path": "/", "sameSite": "Lax", "secure": false, "value": "dk.m.c.ws.fst."}, {"domain": ".aritzia.com", "expiry": 1723918880, "httpOnly": false, "name": "_dyid", "path": "/", "sameSite": "Lax", "secure": false, "value": "6345572130089426158"}, {"domain": ".aritzia.com", "expiry": 1729102870, "httpOnly": false, "name": "AritziaTC", "path": "/", "sameSite": "None", "secure": true, "value": "true"}, {"domain": "www.aritzia.com", "httpOnly": false, "name": "cqcid", "path": "/", "sameSite": "None", "secure": true, "value": "bcMaDvqNiLRscbD5XPNh6qCIIb"}, {"domain": ".aritzia.com", "expiry": 1723918880, "httpOnly": false, "name": "_dycnst", "path": "/", "sameSite": "Lax", "secure": false, "value": "dg"}, {"domain": ".aritzia.com", "expiry": 1755022829, "httpOnly": false, "name": "_ttp", "path": "/", "sameSite": "Lax", "secure": false, "value": "HQAM8uJHE2cshhMUxtFlIWhamRe"}, {"domain": ".aritzia.com", "expiry": 1755886880, "httpOnly": false, "name": "_ga", "path": "/", "sameSite": "None", "secure": true, "value": "GA1.1.369897375.1721326829"}, {"domain": ".aritzia.com", "expiry": 1721329280, "httpOnly": false, "name": "_dy_csc_ses", "path": "/", "sameSite": "Lax", "secure": false, "value": "ubda7siijcokdf9eprjriu9fbg87cy1o"}, {"domain": ".aritzia.com", "httpOnly": false, "name": "dy_fs_page", "path": "/", "sameSite": "Lax", "secure": false, "value": "www.aritzia.com"}, {"domain": ".aritzia.com", "expiry": 1723918880, "httpOnly": false, "name": "__cq_seg", "path": "/", "sameSite": "Lax", "secure": false, "value": "0~0.00!1~0.00!2~0.00!3~0.00!4~0.00!5~0.00!6~0.00!7~0.00!8~0.00!9~0.00"}, {"domain": "www.aritzia.com", "httpOnly": true, "name": "dwsid", "path": "/", "sameSite": "None", "secure": true, "value": "b_AG9-dpQJVgsXyUr8JdBFrVo5WC0HSi2rJesZFnWJ_i74zoUGMd6FeUYVj2iW1-KeM_JFMblOvmmne0PEz_cw=="}, {"domain": "www.aritzia.com", "httpOnly": false, "name": "dw", "path": "/", "sameSite": "Lax", "secure": false, "value": "1"}, {"domain": ".aritzia.com", "expiry": 1755886881, "httpOnly": false, "name": "_ga_E6LWQ64Q02", "path": "/", "sameSite": "None", "secure": true, "value": "GS1.1.1721326829.1.1.1721326881.0.0.0"}, {"domain": ".aritzia.com", "expiry": 1729102825, "httpOnly": false, "name": "_gcl_au", "path": "/", "sameSite": "Lax", "secure": false, "value": "1.1.2107290806.1721326825"}, {"domain": "www.aritzia.com", "httpOnly": false, "name": "__cq_dnt", "path": "/", "sameSite": "None", "secure": true, "value": "0"}, {"domain": "www.aritzia.com", "httpOnly": false, "name": "dw_dnt", "path": "/", "sameSite": "None", "secure": true, "value": "0"}, {"domain": "www.aritzia.com", "httpOnly": false, "name": "cquid", "path": "/", "sameSite": "None", "secure": true, "value": "||"}, {"domain": ".aritzia.com", "expiry": 1721327248, "httpOnly": false, "name": "__wid", "path": "/", "sameSite": "Lax", "secure": false, "value": "889058038"}, {"domain": ".aritzia.com", "expiry": 1721328680, "httpOnly": false, "name": "_dyjsession", "path": "/", "sameSite": "Lax", "secure": false, "value": "ubda7siijcokdf9eprjriu9fbg87cy1o"}, {"domain": ".aritzia.com", "expiry": 1755886879, "httpOnly": false, "name": "OptanonAlertBoxClosed", "path": "/", "sameSite": "Lax", "secure": false, "value": "2024-07-18T18:21:19.264Z"}, {"domain": ".aritzia.com", "expiry": 1755454880, "httpOnly": false, "name": "__cq_uuid", "path": "/", "sameSite": "Lax", "secure": false, "value": "bcMaDvqNiLRscbD5XPNh6qCIIb"}, {"domain": "www.aritzia.com", "expiry": 1722536436, "httpOnly": false, "name": "region-matchhas-been-closed", "path": "/", "sameSite": "None", "secure": true, "value": "true"}, {"domain": ".aritzia.com", "expiry": 1723918822, "httpOnly": false, "name": "AritziaSiteCookie", "path": "/", "sameSite": "None", "secure": true, "value": "Aritzia_CA|ca|en_CA"}, {"domain": ".aritzia.com", "expiry": 1755022829, "httpOnly": false, "name": "_tt_enable_cookie", "path": "/", "sameSite": "Lax", "secure": false, "value": "1"}, {"domain": ".aritzia.com", "expiry": 1723918880, "httpOnly": false, "name": "_dy_geo", "path": "/", "sameSite": "Lax", "secure": false, "value": "US.NA.US_CA.US_CA_Los%20Angeles"}, {"domain": ".aritzia.com", "expiry": 1721328622, "httpOnly": true, "name": "__cf_bm", "path": "/", "sameSite": "None", "secure": true, "value": "bu7d9Y2EhKvZY2C2cYRZyE0BL4enbhx.LZTCej8J0Ac-1721326822-1.0.1.1-_bDTnyghiqL7VUyZ0qEZLXuFrOitvSQJ3EdQiqMG65xC5hu7BbZJ6MAKYK4iMSXyso.pHgdJW3.tQdwaVZbDDw"}, {"domain": ".aritzia.com", "httpOnly": false, "name": "scarab.visitor", "path": "/", "sameSite": "Lax", "secure": false, "value": "%225625C653959040F7%22"}, {"domain": ".aritzia.com", "expiry": 1752862880, "httpOnly": false, "name": "_dy_soct", "path": "/", "sameSite": "Lax", "secure": false, "value": "794383.1501580.1721326880"}, {"domain": "www.aritzia.com", "httpOnly": false, "name": "dwac_bccBUiaagYFO6aaacZXJ6E64UQ", "path": "/", "sameSite": "None", "secure": true, "value": "K60a93uKuc53HrieiXJUdR6Iv5UeM435zR0%3D|dw-only|||CAD|false|Canada%2FPacific|true"}, {"domain": "www.aritzia.com", "expiry": 1736878822, "httpOnly": false, "name": "dwanonymous_2229be5ea6f3843440b278529e0389ad", "path": "/", "sameSite": "None", "secure": true, "value": "bcMaDvqNiLRscbD5XPNh6qCIIb"}, {"domain": ".aritzia.com", "expiry": 1752862879, "httpOnly": false, "name": "_dyid_server", "path": "/", "sameSite": "None", "secure": true, "value": "6345572130089426158"}, {"domain": "www.aritzia.com", "httpOnly": false, "name": "sid", "path": "/", "sameSite": "None", "secure": true, "value": "K60a93uKuc53HrieiXJUdR6Iv5UeM435zR0"}]