[{"domain": "www.ozone.bg", "expiry": 1757350823, "httpOnly": false, "name": "IS_FUNCTIONAL_NEW", "path": "/", "sameSite": "Lax", "secure": false, "value": "1"}, {"domain": "www.ozone.bg", "expiry": 1757350823, "httpOnly": false, "name": "IS_PRODUCTIVE_NEW", "path": "/", "sameSite": "Lax", "secure": false, "value": "1"}, {"domain": "www.ozone.bg", "expiry": 1757350823, "httpOnly": false, "name": "ACCEPT_COOKIE_NEW", "path": "/", "sameSite": "Lax", "secure": false, "value": "1"}, {"domain": ".ozone.bg", "expiry": 1722792617, "httpOnly": false, "name": "_hjSession_151947", "path": "/", "sameSite": "None", "secure": true, "value": "eyJpZCI6IjFhZGQxZTM4LTFiNjktNDc1Yi04NDU1LTJiNjEwNDc1NmY2NyIsImMiOjE3MjI3OTA4MTcxMDAsInMiOjAsInIiOjAsInNiIjowLCJzciI6MCwic2UiOjAsImZzIjoxLCJzcCI6MX0="}, {"domain": "www.ozone.bg", "expiry": 1757350823, "httpOnly": false, "name": "IS_MARKETING_NEW", "path": "/", "sameSite": "Lax", "secure": false, "value": "1"}, {"domain": ".ozone.bg", "expiry": 1754326817, "httpOnly": false, "name": "_hjSessionUser_151947", "path": "/", "sameSite": "None", "secure": true, "value": "eyJpZCI6IjMxMTQ2MzU5LWVmYzgtNWNhNi05YTkzLTY5MGFmNDNhM2QxYiIsImNyZWF0ZWQiOjE3MjI3OTA4MTcxMDAsImV4aXN0aW5nIjpmYWxzZX0="}, {"domain": ".ozone.bg", "expiry": 1722790876, "httpOnly": false, "name": "_gat", "path": "/", "sameSite": "Lax", "secure": false, "value": "1"}, {"domain": ".ozone.bg", "expiry": 1722877215, "httpOnly": false, "name": "_clsk", "path": "/", "sameSite": "Lax", "secure": false, "value": "10y13qw%7C1722790815030%7C1%7C1%7Cq.clarity.ms%2Fcollect"}, {"domain": ".ozone.bg", "expiry": 1756486815, "httpOnly": false, "name": "_ttp", "path": "/", "sameSite": "Lax", "secure": false, "value": "R6QFPSTfIzBSl76z6aTxnf9HUJr"}, {"domain": ".ozone.bg", "expiry": 1730566815, "httpOnly": false, "name": "_rdt_uuid", "path": "/", "sameSite": "Strict", "secure": true, "value": "1722790815169.04d9238a-2cad-4c3d-aabb-d9ebd335b904"}, {"domain": ".www.ozone.bg", "expiry": 1722812420, "httpOnly": true, "name": "frontend_cid", "path": "/", "sameSite": "Lax", "secure": true, "value": "isLZ9PVDXKwJaOa1"}, {"domain": ".ozone.bg", "expiry": 1722877216, "httpOnly": false, "name": "_gid", "path": "/", "sameSite": "Lax", "secure": false, "value": "GA1.2.542297263.1722790815"}, {"domain": ".ozone.bg", "expiry": 1756486816, "httpOnly": false, "name": "_uetvid", "path": "/", "sameSite": "Lax", "secure": false, "value": "0560a210528311ef87f0eb519351b343|15sfyl1|1722790816304|1|1|bat.bing.com/p/insights/c/q"}, {"domain": ".ozone.bg", "expiry": 1722877215, "httpOnly": false, "name": "_uetsid", "path": "/", "sameSite": "Lax", "secure": false, "value": "05606990528311ef99f9cf75a965f936|1c9fu4r|2|fo1|0|1677"}, {"domain": ".ozone.bg", "expiry": 1754326814, "httpOnly": false, "name": "_clck", "path": "/", "sameSite": "Lax", "secure": false, "value": "wv0171%7C2%7Cfo1%7C0%7C1677"}, {"domain": ".ozone.bg", "expiry": 1730566823, "httpOnly": false, "name": "_fbp", "path": "/", "sameSite": "Lax", "secure": false, "value": "fb.1.1722790814115.236808034738901896"}, {"domain": "www.ozone.bg", "expiry": 1722812412, "httpOnly": false, "name": "IS_SID", "path": "/", "sameSite": "Lax", "secure": false, "value": "1"}, {"domain": ".ozone.bg", "expiry": 1757350816, "httpOnly": false, "name": "_ga", "path": "/", "sameSite": "Lax", "secure": false, "value": "GA1.2.2001911744.1722790814"}, {"domain": ".ozone.bg", "expiry": 1722790875, "httpOnly": false, "name": "_gat_gtag_UA_40551915_1", "path": "/", "sameSite": "Lax", "secure": false, "value": "1"}, {"domain": ".ozone.bg", "expiry": 1730566814, "httpOnly": false, "name": "_gcl_au", "path": "/", "sameSite": "Lax", "secure": false, "value": "1.1.1343905812.1722790814"}, {"domain": ".ozone.bg", "expiry": 1757350815, "httpOnly": false, "name": "_ga_PSP0Z71129", "path": "/", "sameSite": "Lax", "secure": false, "value": "GS1.1.1722790813.1.0.1722790815.58.0.379071329"}, {"domain": ".ozone.bg", "expiry": 1756486815, "httpOnly": false, "name": "_tt_enable_cookie", "path": "/", "sameSite": "Lax", "secure": false, "value": "1"}, {"domain": ".www.ozone.bg", "expiry": 1722812420, "httpOnly": true, "name": "frontend", "path": "/", "sameSite": "Lax", "secure": false, "value": "rhod74jodtemb75vchm7fgi40e"}]