[{"domain": "www.long-mcquade.com", "expiry": 1722612660, "httpOnly": false, "name": "__attentive_ss_referrer", "path": "/", "sameSite": "Lax", "secure": true, "value": "ORGANIC"}, {"domain": ".long-mcquade.com", "expiry": 1730386860, "httpOnly": false, "name": "_fbp", "path": "/", "sameSite": "Lax", "secure": false, "value": "fb.1.1722610860558.584610000634509622"}, {"domain": "www.long-mcquade.com", "expiry": 1757170860, "httpOnly": false, "name": "__attentive_id", "path": "/", "sameSite": "Lax", "secure": true, "value": "2c1a659a2f414887bfa0be679d417bdc"}, {"domain": "www.long-mcquade.com", "expiry": 1757170860, "httpOnly": false, "name": "_attn_", "path": "/", "sameSite": "Strict", "secure": true, "value": "eyJ1Ijoie1wiY29cIjoxNzIyNjEwODYwNTA5LFwidW9cIjoxNzIyNjEwODYwNTA5LFwibWFcIjoyMTkwMCxcImluXCI6ZmFsc2UsXCJ2YWxcIjpcIjJjMWE2NTlhMmY0MTQ4ODdiZmEwYmU2NzlkNDE3YmRjXCJ9In0="}, {"domain": ".long-mcquade.com", "expiry": 1722611460, "httpOnly": false, "name": "__utmt", "path": "/", "sameSite": "Lax", "secure": false, "value": "1"}, {"domain": ".long-mcquade.com", "expiry": 1738378860, "httpOnly": false, "name": "__utmz", "path": "/", "sameSite": "Lax", "secure": false, "value": "20348709.1722610860.1.1.utmcsr=(direct)|utmccn=(direct)|utmcmd=(none)"}, {"domain": "www.long-mcquade.com", "expiry": 1722612660, "httpOnly": false, "name": "__attentive_pv", "path": "/", "sameSite": "Lax", "secure": true, "value": "1"}, {"domain": ".long-mcquade.com", "expiry": 1757170859, "httpOnly": false, "name": "_ga_BE9MNQKDV7", "path": "/", "sameSite": "Lax", "secure": false, "value": "GS1.1.1722610859.1.0.1722610859.60.0.0"}, {"domain": ".long-mcquade.com", "expiry": 1730386860, "httpOnly": false, "name": "_gcl_au", "path": "/", "sameSite": "Lax", "secure": false, "value": "1.1.1765717597.1722610860"}, {"domain": ".long-mcquade.com", "httpOnly": false, "name": "__utmc", "path": "/", "sameSite": "Lax", "secure": false, "value": "20348709"}, {"domain": ".long-mcquade.com", "expiry": 1757170859, "httpOnly": false, "name": "_ga", "path": "/", "sameSite": "Lax", "secure": false, "value": "GA1.1.242605730.1722610860"}, {"domain": "www.long-mcquade.com", "expiry": 1722697261, "httpOnly": false, "name": "__attentive_dv", "path": "/", "sameSite": "Lax", "secure": true, "value": "1"}, {"domain": ".long-mcquade.com", "expiry": 1722612660, "httpOnly": false, "name": "__utmb", "path": "/", "sameSite": "Lax", "secure": false, "value": "20348709.1.10.1722610860"}, {"domain": "www.long-mcquade.com", "httpOnly": false, "name": "webp", "path": "/", "sameSite": "Lax", "secure": false, "value": "1"}, {"domain": "www.long-mcquade.com", "expiry": 1723215659, "httpOnly": false, "name": "lang", "path": "/", "sameSite": "Lax", "secure": false, "value": "en"}, {"domain": "www.long-mcquade.com", "expiry": 1757170860, "httpOnly": false, "name": "__attentive_cco", "path": "/", "sameSite": "Lax", "secure": false, "value": "1722610860510"}, {"domain": ".long-mcquade.com", "expiry": 1757170860, "httpOnly": false, "name": "__utma", "path": "/", "sameSite": "Lax", "secure": false, "value": "20348709.242605730.1722610860.1722610860.1722610860.1"}, {"domain": "www.long-mcquade.com", "httpOnly": false, "name": "Lm722stores", "path": "/", "sameSite": "Lax", "secure": false, "value": "b8r1vi86tisfrf6464ghu76t0n"}]