[{"domain": ".protothema.gr", "expiry": 1757352512, "httpOnly": false, "name": "_ga_4EP1CV99H9", "path": "/", "sameSite": "Lax", "secure": false, "value": "GS1.1.1722792496.1.1.1722792512.44.0.0"}, {"domain": ".protothema.gr", "expiry": 1757352512, "httpOnly": false, "name": "_ga_B3L5NF4TWY", "path": "/", "sameSite": "Lax", "secure": false, "value": "GS1.1.1722792496.1.1.1722792512.44.0.675510351"}, {"domain": ".protothema.gr", "expiry": 1756920512, "httpOnly": false, "name": "_chartbeat2", "path": "/", "sameSite": "Lax", "secure": true, "value": ".1722792496218.1722792512183.1.BGowwuB_7DbTCWxockCblyKiCOgky7.1"}, {"domain": ".protothema.gr", "expiry": 1730568510, "httpOnly": false, "name": "_fbp", "path": "/", "sameSite": "Lax", "secure": false, "value": "fb.1.1722792500361.182246537797075442"}, {"domain": ".www.protothema.gr", "expiry": 1756488510, "httpOnly": false, "name": "addtl_consent", "path": "/", "sameSite": "Lax", "secure": true, "value": "1~"}, {"domain": ".protothema.gr", "expiry": 1722792556, "httpOnly": false, "name": "_gat", "path": "/", "sameSite": "Lax", "secure": false, "value": "1"}, {"domain": ".www.protothema.gr", "expiry": 1756488510, "httpOnly": false, "name": "euconsent-v2", "path": "/", "sameSite": "Lax", "secure": true, "value": "CQC060AQC060AAKA1DELBAFgAAAAAAAAAAyIAAAUcgJgA4AM-AjwBKoDfAHbAO5AgoBIgCSgEowJaATHAmSBNICfYFFAKLQUaBRwAAAA.YAAAAAAAAAAA"}, {"domain": ".protothema.gr", "expiry": 1754328509, "httpOnly": false, "name": "FCNEC", "path": "/", "sameSite": "Lax", "secure": false, "value": "%5B%5B%22AKsRol_oRj0JNO_1UYTf0YWgUhu10LEG0dG1GRAID8ngZVBtvsgN45fiJ071FYQwthkHBr4WA1e-rCpO0vyJPz6By_QDgn0_xaQWD2DrarS9sI9ifnySQI1iH3_sJWnpFNo3gxvO_mcslsmV5f1gPm0dvld7haCtaQ%3D%3D%22%5D%5D"}, {"domain": ".protothema.gr", "expiry": 1722792566, "httpOnly": false, "name": "_chartbeat5", "path": "/", "sameSite": "Lax", "secure": true, "value": "1806|938|%2F|https%3A%2F%2Fwww.protothema.gr%2F|C4Zq7RB1qoT8VEEZg1RVEAkaxvB||c|DM3tESDUiJiqCM1cmqCEHI-zBWH8BJ|protothema.gr|"}, {"domain": "www.protothema.gr", "httpOnly": false, "name": "_usplit", "path": "/", "sameSite": "Lax", "secure": false, "value": "A"}, {"domain": "www.protothema.gr", "httpOnly": false, "name": "_ppid", "path": "/", "sameSite": "Lax", "secure": false, "value": "be80f97b1b05e86298eb9f42063b0360"}, {"domain": ".protothema.gr", "expiry": 1722794312, "httpOnly": false, "name": "_cb_svref", "path": "/", "sameSite": "Lax", "secure": true, "value": "external"}, {"domain": ".protothema.gr", "expiry": 1730568496, "httpOnly": false, "name": "_gcl_au", "path": "/", "sameSite": "Lax", "secure": false, "value": "1.1.152963182.1722792496"}, {"domain": ".protothema.gr", "expiry": 1757352512, "httpOnly": false, "name": "_ga", "path": "/", "sameSite": "Lax", "secure": false, "value": "GA1.1.777424866.1722792496"}, {"domain": ".protothema.gr", "expiry": 1756920512, "httpOnly": false, "name": "_cb", "path": "/", "sameSite": "Lax", "secure": true, "value": "CK6dO6DmC_RMzpSjJ"}, {"domain": ".protothema.gr", "expiry": 1722878912, "httpOnly": false, "name": "_gid", "path": "/", "sameSite": "Lax", "secure": false, "value": "GA1.2.1327889602.1722792496"}]