[{"domain": ".sme.sk", "expiry": 1722888601, "httpOnly": false, "name": "campaigns_session", "path": "/", "sameSite": "Lax", "secure": false, "value": "{\"EqHFDp\":{\"sn\":2,\"ut\":1722887701},\"MWH4sx\":{\"sn\":2,\"ut\":1722887701},\"LvrFhR\":{\"sn\":2,\"ut\":1722887701},\"V3IRgJ\":{\"sn\":2,\"ut\":1722887701},\"8wcp1q\":{\"sn\":1,\"ut\":1722887666},\"cHro61\":{\"sn\":2,\"ut\":1722887701}}"}, {"domain": ".sme.sk", "expiry": 1722889500, "httpOnly": false, "name": "deepbi_user_session", "path": "/", "sameSite": "Lax", "secure": false, "value": "4989cdd4-79a8-441b-8f7b-22e2211fa2e6|15"}, {"domain": ".sme.sk", "expiry": 1731527685, "httpOnly": false, "name": "ppcnst_dsgr", "path": "/", "sameSite": "Lax", "secure": true, "value": "{\"t\":1722887685}"}, {"domain": ".sme.sk", "httpOnly": false, "name": "deepbi_user_deepcookie", "path": "/", "sameSite": "None", "secure": true, "value": "lzheu4nr-1l0fan5"}, {"domain": ".sme.sk", "expiry": 1754423701, "httpOnly": false, "name": "campaigns", "path": "/", "sameSite": "Lax", "secure": false, "value": "{\"ey1fL0\":{\"sn\":0,\"ct\":2,\"ut\":1722887701},\"0SlGG8\":{\"sn\":0,\"ct\":2,\"ut\":1722887701},\"cHro61\":{\"sn\":2,\"ct\":2,\"vi\":\"m6L527\",\"bi\":\"Q1BsT4\",\"ut\":1722887701},\"EqHFDp\":{\"sn\":2,\"ct\":2,\"vi\":\"MgpPN4\",\"bi\":\"XXVy3e\",\"ut\":1722887701},\"IcPaLF\":{\"sn\":0,\"ct\":2,\"ut\":1722887701},\"AYjGAV\":{\"sn\":0,\"ct\":2,\"ut\":1722887701},\"8wcp1q\":{\"sn\":1,\"ct\":2,\"vi\":\"Z5M8IO\",\"bi\":\"tiH0Q4\",\"ut\":1722887701},\"LvrFhR\":{\"sn\":2,\"ct\":2,\"vi\":\"JNIb4A\",\"bi\":\"iCG7is\",\"ut\":1722887701},\"MWH4sx\":{\"sn\":2,\"ct\":2,\"vi\":\"f8pvYZ\",\"bi\":\"dEoMvd\",\"ut\":1722887701},\"V3IRgJ\":{\"sn\":2,\"ct\":2,\"vi\":\"qK5NMH\",\"bi\":\"0Boxjc\",\"ut\":1722887701}}"}, {"domain": ".sme.sk", "expiry": 1754423701, "httpOnly": false, "name": "browser_id", "path": "/", "sameSite": "Lax", "secure": false, "value": "7111c6dd-a3c8-41fd-be79-523c3fd1124f"}, {"domain": ".sme.sk", "expiry": 1730663672, "httpOnly": false, "name": "_gcl_au", "path": "/", "sameSite": "Lax", "secure": false, "value": "1.1.11653607.1722887672"}, {"domain": ".sme.sk", "expiry": 1754423699, "httpOnly": false, "name": "deepbi_firstparty_cookie", "path": "/", "sameSite": "Lax", "secure": false, "value": "clzheu3vi0j3bcu5gjl"}, {"domain": ".sme.sk", "expiry": 1730663661, "httpOnly": false, "name": "pp_split_test", "path": "/", "sameSite": "Lax", "secure": false, "value": "9127"}, {"domain": ".sme.sk", "expiry": 1722888601, "httpOnly": false, "name": "remp_session_id", "path": "/", "sameSite": "Lax", "secure": false, "value": "4f413879-b4e0-4820-849a-3446db76a72b"}, {"domain": ".sme.sk", "httpOnly": false, "name": "consent.fulsome", "path": "/", "sameSite": "Lax", "secure": false, "value": "true"}, {"domain": ".sme.sk", "expiry": 1738439667, "httpOnly": false, "name": "__eoi", "path": "/", "sameSite": "None", "secure": true, "value": "ID=5ced68bd6a491341:T=1722887667:RT=1722887667:S=AA-AfjYXYNNmUMCepo2mtTk1AwWs"}, {"domain": ".sme.sk", "expiry": 1757015678, "httpOnly": false, "name": "__gfp_64b", "path": "/", "sameSite": "Lax", "secure": false, "value": "U4InNmnYkYI.SB3Zf7niFcYgG7qDIsjs2Du4eU99Yyf.67|1722887678|2"}, {"domain": ".sme.sk", "expiry": 1756583667, "httpOnly": false, "name": "__gpi", "path": "/", "sameSite": "None", "secure": true, "value": "UID=00000e9a963c93ea:T=1722887667:RT=1722887667:S=ALNI_MYuBwd-yX7xe8mvSuJKUcCFVyUCFg"}, {"domain": ".sme.sk", "expiry": 1756583667, "httpOnly": false, "name": "__gads", "path": "/", "sameSite": "None", "secure": true, "value": "ID=e5c255986df19533:T=1722887667:RT=1722887667:S=ALNI_MYkysMMyYowRemnBRT4xBHMn6Epyw"}]