[{"domain": ".www.gov.uk", "expiry": 1758046199, "httpOnly": false, "name": "_ga_S5RQ7FTGVR", "path": "/", "sameSite": "Lax", "secure": false, "value": "GS1.3.1723486190.1.1.1723486199.0.0.0"}, {"domain": "www.gov.uk", "expiry": 1755022198, "httpOnly": false, "name": "cookies_policy", "path": "/", "sameSite": "Lax", "secure": true, "value": "{\"essential\":true,\"settings\":false,\"usage\":false,\"campaigns\":false}"}, {"domain": "www.gov.uk", "expiry": 1723487992, "httpOnly": false, "name": "lux_uid", "path": "/", "sameSite": "Lax", "secure": false, "value": "172348618935965853"}, {"domain": "www.gov.uk", "expiry": 1723572589, "httpOnly": false, "name": "ABTest-BankHolidaysTest", "path": "/", "sameSite": "Lax", "secure": true, "value": "A"}, {"domain": ".www.gov.uk", "expiry": 1758046192, "httpOnly": false, "name": "_ga", "path": "/", "sameSite": "Lax", "secure": false, "value": "GA1.3.1182747234.1723486190"}, {"domain": "www.gov.uk", "expiry": 1755022198, "httpOnly": false, "name": "cookies_preferences_set", "path": "/", "sameSite": "Lax", "secure": true, "value": "true"}]