[{"domain": "www.blikk.hu", "httpOnly": false, "name": "animatedSubheader", "path": "/", "sameSite": "Lax", "secure": false, "value": "true"}, {"domain": ".blikk.hu", "expiry": 1721469068, "httpOnly": false, "name": "ats_ri", "path": "/", "sameSite": "None", "secure": true, "value": "fp_ms=1716025868947&ri=&model=&models=eyJhdHNfcmkiOm51bGx9&ttl_ms=3600000&expires_ms=1716115868982&version=1716112269.021"}, {"domain": ".blikk.hu", "expiry": 1723888268, "httpOnly": false, "name": "_fbp", "path": "/", "sameSite": "Lax", "secure": false, "value": "fb.1.1716112268909.475456138"}, {"domain": ".blikk.hu", "expiry": 1747648268, "httpOnly": false, "name": "_ga", "path": "/", "sameSite": "Lax", "secure": false, "value": "GA1.1.370158607.1716112268"}, {"domain": ".blikk.hu", "expiry": 1747648268, "httpOnly": false, "name": "_ga_E1YK2YXDPS", "path": "/", "sameSite": "Lax", "secure": false, "value": "GS1.1.1716112268.1.0.1716112268.0.0.0"}, {"domain": "www.blikk.hu", "expiry": 1750672268, "httpOnly": false, "name": "_sotmpid", "path": "/", "sameSite": "Strict", "secure": true, "value": "0:lwdcxp4w:AvyxjavixP7tMICeYwI0aS7kAy0k7mfI"}, {"domain": "www.blikk.hu", "expiry": 1747648268, "httpOnly": false, "name": "color_scheme", "path": "/", "sameSite": "Lax", "secure": false, "value": "lightmode"}, {"domain": ".blikk.hu", "expiry": 1750672268, "httpOnly": false, "name": "_ga_9J3Q331SCQ", "path": "/", "sameSite": "Lax", "secure": false, "value": "GS1.1.1716112268.1.0.1716112268.0.0.0"}, {"domain": "www.blikk.hu", "expiry": 1747648268, "httpOnly": false, "name": "sailthru_visitor", "path": "/", "sameSite": "Lax", "secure": false, "value": "897c8186-420a-45f3-b5ad-73ba8b32e1e5"}, {"domain": "www.blikk.hu", "expiry": 1716114068, "httpOnly": false, "name": "_sotmsid", "path": "/", "sameSite": "Strict", "secure": true, "value": "0:lwdcxp4w:IPWC7Bu62CnT7Zi7G~v91s62t24KLImr"}, {"domain": ".blikk.hu", "expiry": 1750672268, "httpOnly": false, "name": "ea_uuid", "path": "/", "sameSite": "None", "secure": true, "value": "202405191151087790201558"}, {"domain": "www.blikk.hu", "expiry": 1750672268, "httpOnly": false, "name": "kt_uniqueWebClientId", "path": "/", "sameSite": "Lax", "secure": false, "value": "cace53c8-31c3-4f0d-82a3-bfb1f2a967d6"}, {"domain": "www.blikk.hu", "expiry": 1716114067, "httpOnly": false, "name": "sailthru_pageviews", "path": "/", "sameSite": "Lax", "secure": false, "value": "1"}, {"domain": "www.blikk.hu", "expiry": 1747648267, "httpOnly": false, "name": "acc_segment", "path": "/", "sameSite": "None", "secure": true, "value": "11"}]