[{"domain": ".hhs.gov", "expiry": 1753017279, "httpOnly": false, "name": "_ga_3YLR8EGLBW", "path": "/", "sameSite": "Strict", "secure": true, "value": "GS1.1.1718457260.1.1.1718457279.41.0.0"}, {"domain": ".hhs.gov", "expiry": 1749993279, "httpOnly": false, "name": "_ce.s", "path": "/", "sameSite": "Strict", "secure": false, "value": "v~c4fc878b70d4f22fe10a2e262d60282cfb766fe5~lcw~1718457279403~lva~1718457260584~vpv~0~v11.fhb~1718457260846~v11.lhb~1718457279177~v11.cs~1944~v11.s~2d72f4e0-2b19-11ef-b144-2f9aa01292f3~v11.sla~1718457279416~lcw~1718457279416"}, {"domain": ".hhs.gov", "expiry": 1753017279, "httpOnly": false, "name": "_ga", "path": "/", "sameSite": "Strict", "secure": true, "value": "GA1.1.1399278055.1718457260"}, {"domain": "www.hhs.gov", "httpOnly": false, "name": "QSI_HistorySession", "path": "/", "sameSite": "Lax", "secure": true, "value": "https%3A%2F%2Fwww.hhs.gov%2F~1718457261712"}, {"domain": ".hhs.gov", "expiry": 1718543660, "httpOnly": false, "name": "_ce.clock_data", "path": "/", "sameSite": "Strict", "secure": false, "value": "22%2C212.102.63.121%2C1%2C10f9287deaf609ee36fb37783f2b89c0%2CChrome%2CGB"}, {"domain": ".hhs.gov", "expiry": 1718457320, "httpOnly": false, "name": "_gat_GSA_ENOR1", "path": "/", "sameSite": "Strict", "secure": true, "value": "1"}, {"domain": ".hhs.gov", "expiry": 1753017279, "httpOnly": false, "name": "_ga_8RZ83J1052", "path": "/", "sameSite": "Lax", "secure": false, "value": "GS1.1.1718457260.1.1.1718457279.41.0.0"}, {"domain": ".hhs.gov", "httpOnly": false, "name": "cebsp_", "path": "/", "sameSite": "Strict", "secure": false, "value": "2"}, {"domain": ".hhs.gov", "httpOnly": false, "name": "cebs", "path": "/", "sameSite": "Strict", "secure": false, "value": "1"}, {"domain": ".hhs.gov", "httpOnly": false, "name": "_ce.irv", "path": "/", "sameSite": "Strict", "secure": false, "value": "new"}, {"domain": ".hhs.gov", "expiry": 1718457320, "httpOnly": false, "name": "_gat_GSA_ENOR0", "path": "/", "sameSite": "Strict", "secure": true, "value": "1"}, {"domain": ".hhs.gov", "expiry": 1753017279, "httpOnly": false, "name": "_ga_CSLL4ZEK4L", "path": "/", "sameSite": "Strict", "secure": true, "value": "GS1.1.1718457260.1.1.1718457279.0.0.0"}, {"domain": ".www.hhs.gov", "expiry": 1719062078, "httpOnly": false, "name": "RT", "path": "/", "sameSite": "Lax", "secure": false, "value": "\"z=1&dm=www.hhs.gov&si=0a60d2f1-6fb1-4ece-8d90-9d6e57044bd9&ss=lxg52zpe&sl=1&tt=17r&rl=1\""}, {"domain": ".hhs.gov", "expiry": 1718543660, "httpOnly": false, "name": "_ce.clock_event", "path": "/", "sameSite": "Strict", "secure": false, "value": "1"}, {"domain": ".hhs.gov", "expiry": 1718543679, "httpOnly": false, "name": "_gid", "path": "/", "sameSite": "Strict", "secure": true, "value": "GA1.2.1667083638.1718457260"}]