[{"domain": ".therange.co.uk", "expiry": 1748792438, "httpOnly": false, "name": "_pin_unauth", "path": "/", "sameSite": "Lax", "secure": false, "value": "dWlkPU56TmtaRE0wT0RRdFpUVXlPQzAwTnpkaExUaGxNMkl0TXpVME5HVXpOVGhrWmpVMw"}, {"domain": ".therange.co.uk", "expiry": 1750952438, "httpOnly": false, "name": "_tt_enable_cookie", "path": "/", "sameSite": "Lax", "secure": false, "value": "1"}, {"domain": "www.therange.co.uk", "expiry": 1717342837, "httpOnly": false, "name": "__attentive_dv", "path": "/", "sameSite": "Lax", "secure": true, "value": "1"}, {"domain": ".therange.co.uk", "expiry": 1748792441, "httpOnly": false, "name": "OptanonAlertBoxClosed", "path": "/", "sameSite": "Lax", "secure": false, "value": "2024-06-01T15:40:41.989Z"}, {"domain": "www.therange.co.uk", "expiry": 1717258237, "httpOnly": false, "name": "__attentive_ss_referrer", "path": "/", "sameSite": "Lax", "secure": true, "value": "ORGANIC"}, {"domain": ".therange.co.uk", "expiry": 1748792437, "httpOnly": true, "name": "cf_clearance", "path": "/", "sameSite": "None", "secure": true, "value": "r2nZxHegEqI00hgMUjg.xPw5wXptWRO73HnhQ9vhqcg-1717256437-1.0.1.1-qK9.mZOA0BWvQGs6Ruij2sH3Q3cQqHRcXmdVhpBvH.PydlJ.0_rgEhnjfGJ9kWcj5A127dLeafs4x3MOvI_q6g"}, {"domain": ".therange.co.uk", "expiry": 1719848437, "httpOnly": false, "name": "lantern", "path": "/", "sameSite": "Lax", "secure": false, "value": "41e81fb8-893c-46ca-abc0-2a12ab7afadc"}, {"domain": "www.therange.co.uk", "expiry": 1717258237, "httpOnly": false, "name": "__attentive_pv", "path": "/", "sameSite": "Lax", "secure": true, "value": "1"}, {"domain": ".therange.co.uk", "expiry": 1717258237, "httpOnly": false, "name": "_hjSession_3800094", "path": "/", "sameSite": "None", "secure": true, "value": "eyJpZCI6IjQ0MDJmZWRlLWYwMzAtNDlkYy1hYzZmLTk4ODEyYmU3ZDJjZSIsImMiOjE3MTcyNTY0Mzc4NzIsInMiOjAsInIiOjAsInNiIjowLCJzciI6MCwic2UiOjAsImZzIjoxLCJzcCI6MH0="}, {"domain": ".therange.co.uk", "expiry": 1748792441, "httpOnly": false, "name": "OptanonConsent", "path": "/", "sameSite": "Lax", "secure": false, "value": "isGpcEnabled=0&datestamp=Sat+Jun+01+2024+17%3A40%3A41+GMT%2B0200+(Central+European+Summer+Time)&version=202403.1.0&browserGpcFlag=0&isIABGlobal=false&hosts=&consentId=5ccab98a-0d67-4229-874c-8b0300a034cd&interactionCount=1&isAnonUser=1&landingPath=NotLandingPage&groups=C0001%3A1%2CC0002%3A0%2CC0003%3A0%2CC0005%3A0%2CC0004%3A0"}, {"domain": ".therange.co.uk", "expiry": 1725032438, "httpOnly": false, "name": "_fbp", "path": "/", "sameSite": "Lax", "secure": false, "value": "fb.2.1717256438325.978543747"}, {"domain": ".therange.co.uk", "expiry": 1717342837, "httpOnly": false, "name": "_uetsid", "path": "/", "sameSite": "Lax", "secure": false, "value": "4b0e7f00202d11ef858a5124a8c69157"}, {"domain": ".therange.co.uk", "expiry": 1748792437, "httpOnly": false, "name": "_hjSessionUser_3800094", "path": "/", "sameSite": "None", "secure": true, "value": "eyJpZCI6Ijc2M2E0NGFmLTA1NmYtNTE0MC1hZmJhLTQ3ZDRhMjMxNTZmYiIsImNyZWF0ZWQiOjE3MTcyNTY0Mzc4NzEsImV4aXN0aW5nIjpmYWxzZX0="}, {"domain": ".therange.co.uk", "expiry": 1750952438, "httpOnly": false, "name": "_ttp", "path": "/", "sameSite": "Lax", "secure": false, "value": "SZ4N64SA_CIYYb89AHpap5MU6qd"}, {"domain": "www.therange.co.uk", "expiry": 1751816437, "httpOnly": false, "name": "__attentive_cco", "path": "/", "sameSite": "Lax", "secure": false, "value": "1717256437633"}, {"domain": ".therange.co.uk", "expiry": 1719675637, "httpOnly": true, "name": "si", "path": "/", "sameSite": "None", "secure": true, "value": "13-665b40f59e701"}, {"domain": ".therange.co.uk", "expiry": 1750952437, "httpOnly": false, "name": "_uetvid", "path": "/", "sameSite": "Lax", "secure": false, "value": "4b0eaa80202d11efa35a1f7c9cdcb38f"}, {"domain": "www.therange.co.uk", "expiry": 1751816437, "httpOnly": false, "name": "_attn_", "path": "/", "sameSite": "Strict", "secure": true, "value": "eyJ1Ijoie1wiY29cIjoxNzE3MjU2NDM3NjMyLFwidW9cIjoxNzE3MjU2NDM3NjMyLFwibWFcIjoyMTkwMCxcImluXCI6ZmFsc2UsXCJ2YWxcIjpcIjg0YzlkNjgxYjc5ODRlNWNiYjgxNDgwMDUyYmMzZDM5XCJ9In0="}, {"domain": "www.therange.co.uk", "expiry": 1751816437, "httpOnly": false, "name": "__attentive_id", "path": "/", "sameSite": "Lax", "secure": true, "value": "84c9d681b7984e5cbb81480052bc3d39"}, {"domain": ".therange.co.uk", "expiry": 1717258237, "httpOnly": true, "name": "__cf_bm", "path": "/", "sameSite": "None", "secure": true, "value": "dKsot74TxTEm1wxdizMu1ACItVLpdGE6AK6OIZZGY9I-1717256437-1.0.1.1-sTwkFHFgNw6aXHyp8yxjYfvb43Q1B6RZrWTttO3Qvh6nGdWtAJ6iAtCHjCG6TjdTFcshl7esZvRSSc0uyveI6mYKdvaJvKQ4uHgBaPiTrzk"}]