[{"domain": ".thetimes.co.uk", "expiry": 1744714960, "httpOnly": false, "name": "_nuk_sp_id.16ab", "path": "/", "sameSite": "None", "secure": true, "value": ".1713178954.1.1713178961..98bcd34d-fc6d-48e0-8784-664fa899b781..eadc6823-c9f0-41fa-9ced-ea61c9a5a14e.1713178954255.8"}, {"domain": ".thetimes.co.uk", "expiry": 1713180760, "httpOnly": false, "name": "utag_main__se", "path": "/", "sameSite": "Lax", "secure": false, "value": "13%3Bexp-session"}, {"domain": "www.thetimes.co.uk", "expiry": 1744714957, "httpOnly": false, "name": "consentUUID", "path": "/", "sameSite": "None", "secure": true, "value": "82f64ee0-14dc-4d5b-8fb1-74a6c857e02b_30"}, {"domain": "www.thetimes.co.uk", "expiry": 1747738957, "httpOnly": false, "name": "nukt_sp_consent", "path": "/", "sameSite": "Lax", "secure": false, "value": ""}, {"domain": "www.thetimes.co.uk", "expiry": 1747738960, "httpOnly": false, "name": "nukt_sp_consent_global", "path": "/", "sameSite": "Lax", "secure": false, "value": "GDPR%3A%7C"}, {"domain": "www.thetimes.co.uk", "expiry": 1744714955, "httpOnly": false, "name": "liveagent_vc", "path": "/", "sameSite": "Lax", "secure": false, "value": "2"}, {"domain": ".thetimes.co.uk", "expiry": 1713180760, "httpOnly": false, "name": "utag_main__ss", "path": "/", "sameSite": "Lax", "secure": false, "value": "0%3Bexp-session"}, {"domain": ".thetimes.co.uk", "httpOnly": false, "name": "nuk_customer_region_code", "path": "/", "sameSite": "Lax", "secure": true, "value": "NH"}, {"domain": ".thetimes.co.uk", "expiry": 1744714954, "httpOnly": false, "name": "_ncg_g_id_", "path": "/", "sameSite": "None", "secure": true, "value": "411bdac5-8578-41fe-b387-1bd41c2456a5.3.1713178954.1744714954"}, {"domain": "www.thetimes.co.uk", "expiry": 1747738957, "httpOnly": false, "name": "nukt_sp_vendors", "path": "/", "sameSite": "Lax", "secure": false, "value": "709%2Cfalse%2Cfalse"}, {"domain": "www.thetimes.co.uk", "expiry": 1744714955, "httpOnly": false, "name": "liveagent_oref", "path": "/", "sameSite": "Lax", "secure": false, "value": ""}, {"domain": ".thetimes.co.uk", "expiry": 1744714960, "httpOnly": true, "name": "_nuk_sp_id_", "path": "/", "sameSite": "None", "secure": true, "value": "8aabfebf-fe28-43c7-b744-231d9c03219d"}, {"domain": ".thetimes.co.uk", "expiry": 1744714960, "httpOnly": false, "name": "utag_main__sn", "path": "/", "sameSite": "Lax", "secure": false, "value": "1"}, {"domain": ".thetimes.co.uk", "expiry": 1747738954, "httpOnly": false, "name": "_ga", "path": "/", "sameSite": "Lax", "secure": false, "value": "GA1.3.1980009813.1713178954"}, {"domain": ".thetimes.co.uk", "expiry": 1713265354, "httpOnly": false, "name": "_gid", "path": "/", "sameSite": "Lax", "secure": false, "value": "GA1.3.353912896.1713178954"}, {"domain": ".thetimes.co.uk", "httpOnly": false, "name": "nuk_customer_country_code", "path": "/", "sameSite": "Lax", "secure": true, "value": "NL"}, {"domain": ".thetimes.co.uk", "expiry": 1713180760, "httpOnly": false, "name": "_nuk_sp_ses.16ab", "path": "/", "sameSite": "None", "secure": true, "value": "*"}, {"domain": ".thetimes.co.uk", "expiry": 1744714960, "httpOnly": false, "name": "rc_id2", "path": "/", "sameSite": "None", "secure": true, "value": "018ee16c4985003531533f8d0ff405075001b06d00bd0"}, {"domain": ".thetimes.co.uk", "expiry": 1744714954, "httpOnly": false, "name": "signedLspa", "path": "/", "sameSite": "None", "secure": true, "value": "undefined"}, {"domain": "www.thetimes.co.uk", "expiry": 1744714955, "httpOnly": false, "name": "liveagent_ptid", "path": "/", "sameSite": "Lax", "secure": false, "value": "6ffd3cc2-6bd9-4e52-b184-6a7b8134601d"}, {"domain": ".thetimes.co.uk", "expiry": 1744714954, "httpOnly": false, "name": "ccpaApplies", "path": "/", "sameSite": "None", "secure": true, "value": "false"}, {"domain": ".thetimes.co.uk", "expiry": 1744714954, "httpOnly": false, "name": "nukt_mem", "path": "/", "sameSite": "Lax", "secure": false, "value": "s=1713178954119|ppn=homepage|ppt=homepage|pps=homepage"}, {"domain": ".thetimes.co.uk", "expiry": 1744714954, "httpOnly": false, "name": "_sp_su", "path": "/", "sameSite": "None", "secure": true, "value": "false"}, {"domain": ".thetimes.co.uk", "expiry": 1744714954, "httpOnly": false, "name": "dnsDisplayed", "path": "/", "sameSite": "None", "secure": true, "value": "undefined"}, {"domain": ".thetimes.co.uk", "expiry": 1713180760, "httpOnly": false, "name": "utag_main_ses_id", "path": "/", "sameSite": "Lax", "secure": false, "value": "1713178954119%3Bexp-session"}, {"domain": ".thetimes.co.uk", "expiry": 1747738960, "httpOnly": false, "name": "login_event_fired", "path": "/", "sameSite": "Lax", "secure": false, "value": "false"}, {"domain": "www.thetimes.co.uk", "expiry": 1744714957, "httpOnly": false, "name": "consentDate", "path": "/", "sameSite": "None", "secure": true, "value": "2024-04-15T11:02:37.901Z"}, {"domain": ".thetimes.co.uk", "expiry": 1744714954, "httpOnly": false, "name": "nuPixelApp", "path": "/", "sameSite": "None", "secure": true, "value": "j%3A%7B%22id%22%3A%22a99248a0-fb17-11ee-92f4-fba593121e81%22%7D"}, {"domain": "www.thetimes.co.uk", "expiry": 1747738957, "httpOnly": false, "name": "nukt_sp_consent_v2", "path": "/", "sameSite": "Lax", "secure": false, "value": "%7C"}, {"domain": ".thetimes.co.uk", "expiry": 1744714954, "httpOnly": false, "name": "_ncg_domain_id_", "path": "/", "sameSite": "None", "secure": true, "value": "fce4c1ba-2727-49bd-9a41-4711f6dedd04.1.1713178954.1744714954"}, {"domain": ".thetimes.co.uk", "httpOnly": false, "name": "nuk_customer_location_hint", "path": "/", "sameSite": "Lax", "secure": false, "value": "GLOBAL"}, {"domain": "www.thetimes.co.uk", "expiry": 1713179073, "httpOnly": false, "name": "nuk_ni_statuscode", "path": "/", "sameSite": "Lax", "secure": false, "value": "acsaz-307"}, {"domain": ".thetimes.co.uk", "expiry": 1713180760, "httpOnly": false, "name": "utag_main__pn", "path": "/", "sameSite": "Lax", "secure": false, "value": "1%3Bexp-session"}, {"domain": "www.thetimes.co.uk", "httpOnly": false, "name": "nuk_zephr_decisions", "path": "/", "sameSite": "Lax", "secure": false, "value": "eyJ1bmxvY2stYnktdXJsLS0tZnJlbmNoLWVsZWN0aW9uIjoiTk9fQUNDRVNTIiwidW5sb2NrLWJ5LXVybCI6Ik5PX0FDQ0VTUyIsInRpbWVzLXRyYXZlbC11bmxvY2stYXBpIjoiTk9fQUNDRVNTIiwibmV3LWhvdC1jb2xkLXBheXdhbGwiOiJOT19BQ0NFU1MiLCJoYWxpZmF4LS0tdW5sb2NrLWJwdGwtc2VjdGlvbiI6Ik5PX0FDQ0VTUyIsImNvcnBvcmF0ZS1pcC1hY2Nlc3MiOiJOT19BQ0NFU1MifQ=="}, {"domain": ".thetimes.co.uk", "expiry": 1713180760, "httpOnly": false, "name": "utag_main__st", "path": "/", "sameSite": "Lax", "secure": false, "value": "1713180760916%3Bexp-session"}, {"domain": "www.thetimes.co.uk", "httpOnly": false, "name": "liveagent_sid", "path": "/", "sameSite": "Lax", "secure": false, "value": "6ffd3cc2-6bd9-4e52-b184-6a7b8134601d"}, {"domain": ".thetimes.co.uk", "expiry": 1744714960, "httpOnly": true, "name": "rc_id1", "path": "/", "sameSite": "None", "secure": true, "value": "018ee16c4985003531533f8d0ff405075001b06d00bd0"}, {"domain": ".thetimes.co.uk", "expiry": 1744714960, "httpOnly": false, "name": "utag_main_v_id", "path": "/", "sameSite": "Lax", "secure": false, "value": "018ee16c4985003531533f8d0ff405075001b06d00bd0"}]