[{"domain": ".mass.gov", "expiry": 1753010245, "httpOnly": false, "name": "_4c_", "path": "/", "sameSite": "Lax", "secure": false, "value": "%7B%22_4c_s_%22%3A%22lVPBbpwwEP2VyOf1xjbGsHtLW6nqITmlZ2TsWUDZYGQ70DTaf%2B%2BYhW026aUIgef5zeN5mHkjUws92fOClzJnQuZS8A15gtdA9m%2FEdza9RrInGYNaiULTwhaSSiNLWiqjqMxzCYfSAqst2ZBfSUsogbfMUOu0IWZYNN6IcRZQi%2B%2B2QmwZPQTMiL8TIhguB%2B%2Fsi4lVfB0SbYL6Jtgn3LAwdgaqqbOxnfNn%2BoK20DVtTDArZ3jwKcDV1PXWTR%2FTFvSStmMZorV3U4CU%2BbX17hluuFAIO6wDudcGlx4O4P1MwSh0MXl81iFsGzcuCBZuAekZ7GGqFuoDhndfqgghffXBYQgj9JFfReIqytYoQAid6yvnm7AYWJBBeyS%2B2zCtjrVDZIAe7F%2B3VQDtTVu9hBmdZZujq%2FWx6vV4BQ%2FjUsGjM%2FqYzGOTbMiLP%2BKyjXEI%2B9vbaZq26%2FFvk%2BE%2BZQ0%2BtcGj75oG%2FD3E1iXVR69tF9GuPqY%2FhB2H5bQQuibp2lQQjJ6iG97B3%2B%2Bqnz%2B%2BJSeqLDPG1G576dOMnJZm42WeKSWlzAQ2U0SHpZIsXafzQebe49dsbM3iM%2FvcAxT6%2F0sbu3VIZM2YkXVJs5rhkJQ4KTvLgWpVGBwRlVktyUVS5oLJDB%2BLJC9XRQuHVXKnmTGFklTnllOJErRWxYFaXmhpQQrLGfnoUv7DZSr6WfJdia%2FHNRfI64a4Hv5S7NnjFReRxF0lh49aaf90%2BgM%3D%22%7D"}, {"domain": ".mass.gov", "expiry": 1753010243, "httpOnly": false, "name": "_ga_SW2TVH2WBY", "path": "/", "sameSite": "Lax", "secure": false, "value": "GS1.1.1718450243.1.0.1718450243.0.0.0"}, {"domain": ".mass.gov", "expiry": 1753010243, "httpOnly": false, "name": "_ga", "path": "/", "sameSite": "Lax", "secure": false, "value": "GA1.1.168830069.1718450243"}, {"domain": ".mass.gov", "expiry": 1753010243, "httpOnly": false, "name": "_ga_E2HYQ6TW32", "path": "/", "sameSite": "Lax", "secure": false, "value": "GS1.1.1718450243.1.0.1718450243.0.0.0"}, {"domain": ".mass.gov", "expiry": 1718450303, "httpOnly": false, "name": "_gat_UA-12471675-10", "path": "/", "sameSite": "Lax", "secure": false, "value": "1"}, {"domain": ".mass.gov", "expiry": 1753010244, "httpOnly": false, "name": "nmstat", "path": "/", "sameSite": "Lax", "secure": false, "value": "6f48edd5-b888-dc4f-9c2b-430cf747939f"}, {"domain": ".mass.gov", "expiry": 1718450303, "httpOnly": false, "name": "_gat_UA-12471675-5", "path": "/", "sameSite": "Lax", "secure": false, "value": "1"}, {"domain": ".mass.gov", "expiry": 1718536643, "httpOnly": false, "name": "_gid", "path": "/", "sameSite": "Lax", "secure": false, "value": "GA1.2.1666285976.1718450243"}]