[{"domain": ".saskatchewan.ca", "expiry": 1752432799, "httpOnly": false, "name": "_ga_0TN67B9FEE", "path": "/", "sameSite": "Lax", "secure": false, "value": "GS1.1.1717872797.1.1.1717872799.0.0.0"}, {"domain": ".saskatchewan.ca", "expiry": 1752432799, "httpOnly": false, "name": "_ga", "path": "/", "sameSite": "Lax", "secure": false, "value": "GA1.2.1022053595.1717872798"}, {"domain": ".saskatchewan.ca", "expiry": 1717959199, "httpOnly": false, "name": "_gid", "path": "/", "sameSite": "Lax", "secure": false, "value": "GA1.2.74818989.1717872798"}, {"domain": "www.saskatchewan.ca", "expiry": 1752432798, "httpOnly": true, "name": "SC_ANALYTICS_GLOBAL_COOKIE", "path": "/", "sameSite": "None", "secure": true, "value": "6b0a02bf57c24cb585642289e86f9168|True"}, {"domain": ".saskatchewan.ca", "expiry": 1752432799, "httpOnly": false, "name": "_ga_GCRZCBDDNR", "path": "/", "sameSite": "Lax", "secure": false, "value": "GS1.1.1717872797.1.1.1717872799.0.0.0"}, {"domain": "www.saskatchewan.ca", "httpOnly": true, "name": "ASP.NET_SessionId", "path": "/", "sameSite": "None", "secure": true, "value": "uarm0yehja1pxyhczds3ve1d"}, {"domain": ".saskatchewan.ca", "expiry": 1717872857, "httpOnly": false, "name": "_gat_UA-46191052-1", "path": "/", "sameSite": "Lax", "secure": false, "value": "1"}, {"domain": "www.saskatchewan.ca", "httpOnly": false, "name": "shell#lang", "path": "/", "sameSite": "None", "secure": true, "value": "en"}]