[{"domain": "www.jdsports.co.uk", "expiry": 1748798116, "httpOnly": false, "name": "__rtbh.uid", "path": "/", "sameSite": "Lax", "secure": false, "value": "%7B%22eventType%22%3A%22uid%22%2C%22id%22%3A%22undefined%22%7D"}, {"domain": ".jdsports.co.uk", "expiry": 1727622916, "httpOnly": false, "name": "ckgRM", "path": "/", "sameSite": "Lax", "secure": false, "value": "true"}, {"domain": "www.jdsports.co.uk", "httpOnly": true, "name": "akavpau_VP1", "path": "/", "sameSite": "None", "secure": true, "value": "1717255218~id=d72f51e520be3807b0e81e0274e72809"}, {"domain": "www.jdsports.co.uk", "expiry": 1719846918, "httpOnly": true, "name": "language", "path": "/", "sameSite": "Lax", "secure": true, "value": "en"}, {"domain": "www.jdsports.co.uk", "expiry": 1748798116, "httpOnly": false, "name": "__rtbh.lid", "path": "/", "sameSite": "Lax", "secure": false, "value": "%7B%22eventType%22%3A%22lid%22%2C%22id%22%3A%22SXW4nFiLxeiKZQo0H5yN%22%7D"}, {"domain": "www.jdsports.co.uk", "expiry": 1725030916, "httpOnly": false, "name": "49746", "path": "/", "sameSite": "Lax", "secure": false, "value": ""}]